cogeotiff/__init__.py
cogeotiff/cog.py
cogeotiff/profiles.py
cogeotiff/utils.py
cogeotiff/validate_cogeotiff.py
cogeotiff/cli/__init__.py
cogeotiff/cli/cli.py
cogeotiff/cli/create.py
cogeotiff/cli/validate.py
cogeotiff-0.1.4.dist-info/METADATA
cogeotiff-0.1.4.dist-info/RECORD
cogeotiff-0.1.4.dist-info/WHEEL
cogeotiff-0.1.4.dist-info/entry_points.txt
cogeotiff-0.1.4.dist-info/top_level.txt
