Metadata-Version: 2.1
Name: cogeotiff
Version: 0.1.4
Summary: Cloud Optimized GeoTiff utility tools.
Home-page: https://github.com/sshuair/cogeotiff
Author: sshuair
Author-email: sshuair@gmail.com
License: UNKNOWN
Keywords: GeoTiff COG GDAL
Platform: UNKNOWN
Classifier: Development Status :: 4 - Beta
Classifier: Intended Audience :: Developers
Classifier: Intended Audience :: Information Technology
Classifier: Intended Audience :: Science/Research
Classifier: License :: OSI Approved :: MIT License
Classifier: Programming Language :: Python :: 3.5
Classifier: Programming Language :: Python :: 3.6
Classifier: Programming Language :: Python :: 3
Classifier: Topic :: Multimedia :: Graphics :: Graphics Conversion
Classifier: Topic :: Scientific/Engineering :: GIS
Requires-Dist: click
Requires-Dist: gdal
